safespike/__init__.py
safespike/data_synchronizer.py
safespike/sensor.py
safespike/sensor_data.py
safespike/sensor_tandem.py
safespike/utils.py
safespike-1.5.dist-info/licenses/LICENSE
safespike-1.5.dist-info/METADATA
safespike-1.5.dist-info/WHEEL
safespike-1.5.dist-info/top_level.txt
safespike-1.5.dist-info/RECORD
