Metadata-Version: 2.4
Name: safespike
Version: 1.5
Summary: A module for detecting ACL risk
Author: Sean Ashley
Classifier: Programming Language :: Python :: 3
Classifier: Operating System :: OS Independent
Requires-Python: >=3.6
License-File: LICENSE
Requires-Dist: numpy
Requires-Dist: scipy
Requires-Dist: numpy-quaternion
Requires-Dist: pandas
Dynamic: license-file
